mergetb/__init__.py
mergetb/cred.py
mergetb/grpc_client.py
mergetb/identity.py
mergetb/materialize.py
mergetb/mergetb.py
mergetb/model.py
mergetb/realize.py
mergetb/types.py
mergetb/workspace.py
mergetb/xdc.py
mergetb-1.3.16.dist-info/LICENSE.md
mergetb-1.3.16.dist-info/METADATA
mergetb-1.3.16.dist-info/WHEEL
mergetb-1.3.16.dist-info/top_level.txt
mergetb-1.3.16.dist-info/RECORD
